physiocurve/__init__.py
physiocurve/common/__init__.py
physiocurve/ecg/__init__.py
physiocurve/ecg/wrapper.py
physiocurve/flow/__init__.py
physiocurve/flow/flow.py
physiocurve/flow/wrapper.py
physiocurve/pandas/__init__.py
physiocurve/pandas/ecg.py
physiocurve/pandas/flow.py
physiocurve/pandas/ppg.py
physiocurve/pandas/pressure.py
physiocurve/ppg/__init__.py
physiocurve/ppg/wrapper.py
physiocurve/pressure/__init__.py
physiocurve/pressure/foot.py
physiocurve/pressure/incycle.py
physiocurve/pressure/wrapper.py
physiocurve-2024.12.16.dist-info/LICENSE
physiocurve-2024.12.16.dist-info/METADATA
physiocurve-2024.12.16.dist-info/WHEEL
physiocurve-2024.12.16.dist-info/RECORD
